gpuv/__init__.py
gpuv/__main__.py
gpuv/cli.py
gpuv/extras/__init__.py
gpuv/extras/multiply.py
gpuv/frontend/.gitignore
gpuv/frontend/.vscode/extensions.json
gpuv/frontend/README.md
gpuv/frontend/dist/assets/index-9505d619.js
gpuv/frontend/dist/assets/index-cf0a6d38.css
gpuv/frontend/dist/index.html
gpuv/frontend/dist/vite.svg
gpuv/frontend/index.html
gpuv/frontend/jsconfig.json
gpuv/frontend/package-lock.json
gpuv/frontend/package.json
gpuv/frontend/public/vite.svg
gpuv/frontend/src/App.svelte
gpuv/frontend/src/app.css
gpuv/frontend/src/assets/svelte.svg
gpuv/frontend/src/lib/GPU/GpuDashboard.svelte
gpuv/frontend/src/lib/GPU/SharedLine.svelte
gpuv/frontend/src/lib/GPU/data.js
gpuv/frontend/src/lib/GPU/timeUtils.js
gpuv/frontend/src/main.js
gpuv/frontend/src/vite-env.d.ts
gpuv/frontend/svelte.config.js
gpuv/frontend/vite.config.js
gpuv/nvml.py
gpuv/server.py
gpuv-0.0.10.dist-info/LICENSE
gpuv-0.0.10.dist-info/METADATA
gpuv-0.0.10.dist-info/WHEEL
gpuv-0.0.10.dist-info/entry_points.txt
gpuv-0.0.10.dist-info/RECORD
