Metadata-Version: 2.1
Name: gpuv
Version: 0.0.10
Summary: gpu visualization
License: Apache License
Author: CambioML
Author-email: wanwanaiai45@gmail.com
Maintainer: Jared Wilber
Maintainer-email: jared@cambioml.com
Requires-Python: >=3.8,<4.0
Classifier: License :: Other/Proprietary License
Classifier: Programming Language :: Python :: 3
Classifier: Programming Language :: Python :: 3.8
Classifier: Programming Language :: Python :: 3.9
Classifier: Programming Language :: Python :: 3.10
Classifier: Programming Language :: Python :: 3.11
Requires-Dist: flask (==2.3.3)
Requires-Dist: flask-cors (==4.0.0)
Requires-Dist: pynvml (==11.5.0)
Requires-Dist: typer (==0.9.0)
